{"AudioLength":"0:15","Automated":false,"SoundList":[{"name":"C:\\Git\\SlideshowMaker\\SlideshowMaker\\images\/\/flute+hrn+mrmba.aif"},{"name":"C:\\Git\\SlideshowMaker\\SlideshowMaker\\images\/\/flute+hrn+mrmba.aif"},{"name":"C:\\Git\\SlideshowMaker\\SlideshowMaker\\images\/\/flute+hrn+mrmba.aif"}],"SlideList":[{"imgTime":0,"name":"C:\\Git\\SlideshowMaker\\SlideshowMaker\\images\\46456227_2504829799542273_7554593422053474304_o-700x525.jpg","hasTransitions":false},{"imgTime":0,"name":"C:\\Git\\SlideshowMaker\\SlideshowMaker\\images\\983794168.jpg","hasTransitions":false},{"imgTime":0,"name":"C:\\Git\\SlideshowMaker\\SlideshowMaker\\images\\91Io5sXiDqL.jpg","hasTransitions":false},{"imgTime":0,"name":"C:\\Git\\SlideshowMaker\\SlideshowMaker\\images\\7iPhone-7-plus-water-wallpaper.jpg","hasTransitions":false}]}